bit_notify/__init__.py
bit_notify/notifier.py
bit_notify/sms/__init__.py
bit_notify/sms/sms_client.py
bit_notify-0.1.3.dist-info/DESCRIPTION.rst
bit_notify-0.1.3.dist-info/METADATA
bit_notify-0.1.3.dist-info/RECORD
bit_notify-0.1.3.dist-info/WHEEL
bit_notify-0.1.3.dist-info/metadata.json
bit_notify-0.1.3.dist-info/top_level.txt
